[{"authors":null,"categories":null,"content":"Welcome! I am Yin Zhaoyuan, and you can call me Enjoy. 大鹏一日同风起，抟摇直上九万里。 ————《上李邕》 唐·李白\n","date":33183043200,"expirydate":-62135596800,"kind":"term","lang":"en","lastmod":33183043200,"objectID":"2525497d367e79493fd32b198b28f040","permalink":"","publishdate":"0001-01-01T00:00:00Z","relpermalink":"","section":"authors","summary":"Welcome! I am Yin Zhaoyuan, and you can call me Enjoy. 大鹏一日同风起，抟摇直上九万里。 ———","tags":null,"title":"Yin Zhaoyuan","type":"authors"},{"authors":["Yin Zhaoyuan"],"categories":[],"content":"  ❄️ 2021 December    2021年12月2日  小时候，爸爸常跟我说时间的划分要合理，比如说早点起床就可以给上午留下大块的时间学习。后来学了工业工程，更是把效率和利用率常挂心头。\n所以，有那么一刻我不知道为什么宝贝会晚上六点多来找我学习几个小时，而无妨路上的两个小时。我心疼她挤在地铁里的样子，不想她背着沉重的包越过人海，但当她跟我说不觉得这些是累的时候，我才明白自己还是自私的，总想证明自己爱她多一点，便不能坦然接受她对我的付出。\n这次是我没记住《恋爱守则》第三条了，该打😲。\n因缘巧合把双方家长的礼物都买好了🎁，我们俩一直是最好的安排。\n     🐟 2021 November    2021年11月30日  11月的最后一天当然是跟她在一起的，小东西今天是个大聪明，完美转述了楷爹的意见😃。\n吃完饭她胃胀气顶的不行，然后我就趴在椅子上，让她趴到我的背上，场面一度接近失控，最后看到椅子旁边写着“不准躺卧”😑。\n打电话祝福爸爸妈妈的银婚，说了句我坐在外面，就被发现是和她在一起。爷爷挺喜欢她，夸我眼光好。\n《恋爱守则》第三条：我们是一家人。\n    2021年11月27日  宝贝今天Master毕业典礼，我也穿的人模狗样盛装出席，她捧着绽放的花簇，是人群中最靓的那一个。视频里不仅见到她妈妈，也看到了她的外婆，收获了越来越多家人的祝福。\n晚上两个人吃光了四个菜，喝了一瓶青岛大绿棒，又去破了我们的投篮机记录🏀。就是头发剪得不太齐，像个汉奸一样。\n想给她足够的安全感，把日子定在了2023.1.2，结婚倒计时400天📆。\n    2021年11月25日  由于计划回去见她爸妈，便坚持了几天的饮食控制计划，直白说就是饿了自己几天。\n今天去HKU找宝贝自习，中午她请我吃了顿麻辣香锅 + 武汉热干面🍜，为了跟着宝贝混，三天饿九顿😬。\n    2021年11月23日  我们终于要有自己的小家了。\n下午5:15宝贝跟我说看好了一个房源，然后说要去看下房间。\n我们匆匆忙忙赶到，简单转了一圈，对那个天台挺满意🏰。\n她6:30还要上课，我们又赶紧跑上地铁，然后决定就是这间吧，便付了定金。时间是6:13，离发现房源到交付定金还不到一个小时，这般行事风格，很像我妈妈。\n    2021年11月21日  今天下定决心跟她回温州了，机票也一并订好。\n长大来的就是这么突然，当我把电话打给家里的时候，他们只是说，这些事情应该由我自己决定。是啊，人是我爱的，未来是我选的，见她爸妈和家中长辈也是我期待的，因为我要跟她走一辈子。\n小宝贝也有点蒙，本以为是叫同学来家里玩，但其实是两个家庭的接触吧。\n🐶 ： “我爸妈已经开始安排烟酒了😏” 🐱 ： “？？？别啊，放松放松，我紧张，救命” 六个人里，就她是在过家家🐼。\n    2021年11月20日  她坐了一大圈的车才到石硖尾，小可怜无疑了。十一点还没到就给她饿的前胸贴肚皮了，我们赶紧去翠苑吃点牛肉，可不敢让小家伙饿肚子。\n再次罚宝贝吃冰淇淋🍨，然后她就吃到鼻子上去了，那张照片很适合做壁纸，呆萌中透露着纯真。\n把我的电脑拿给她用了，什么都想给她好一点。\n    2021年11月16日  好久没来巴依，今天吃了好多面。\n罚宝贝吃了个冰淇淋🍨，然后陪她去开通了花旗的账户。\n离她生日越来越近，我也在准备着呢。\n    2021年11月14日  中午去吃了物美价廉的鸡煲放题，唐吉坷德和宜家是我们散步消食的地方。\n跑马地的叮叮车、西营盘的叮叮车，都是阴差阳错。我们坐在顶层车厢的最后，一路聊了好久，从恋爱的美妙到日后的规划。过去的三个月真美好，未来还要更好，牵着手，她这辈子都别想跑。 坚尼地城海岸的夕阳很美，我抱起她，看着波光粼粼的海面，日子就该是这样的🌇。\n    2021年11月13日  和coffee一起去了M+博物馆，我们俩回office的路上被晒成麻瓜。\n小东西下午在瑜伽垫上睡成一个球，仿佛刚进城的拾荒大爷。 晚上吃了心心念念很久的烤鱼。然后去逛了宜家，越来越渴望我们自己的小家了🏩。\n    2021年11月12日  🐱 ： “姨妈虚弱，要你呜呜呜” 🐶 ： “哥哥陪着宝贝，哥哥在” 然后就在公园的摇晃木马上捡到了一只小可爱。故地重游一闪一闪，夜宵喝了青岛啤酒，吃了添宝手撕鸡的牛展。\n    2021年11月11日  🐱 ： “姨妈来了” 🐶 ： “哇 我昨晚做梦 你来姨妈了” 梦里我在地铁里抱着她，她突然说来姨妈了，让我蹲下去，我一看裤子都红了。\n晚上出其不意的冲到了HKU，可惜课表上的教室更新了，没能突然抱住她。下课之后她在common room用微波炉给我做了两杯饺子，微波大王实至名归。\n    2021年11月9日  中午去找宝贝吃了煲仔饭，下午在图书馆外面吃番石榴的时候贡献了“年糕”表情包。\n她给了我弟弟很多英语作文的建议，我发到家人群里。\n嗯，这样下去不结婚很难收场。\n    2021年11月5日  投稿之前，经历了好多次大改，她心疼我，又是订外卖、又是跑过来抱我，为了不打乱我的种种安排，甚至独自在地铁里晃荡了个把小时。知道真相的我欲哭无泪，我心疼这个小人儿，又懊恼于自己的愚钝。\n她的眼泪像彗星一样🎇，瞬息即来，我哄着她，又很快眉开眼笑。她情绪的波动仿佛连在我的心里。我们总是承受了太多来自导师的不确定性。\n    2021年11月3日  🐶 ： “宝贝！！！！！！！！你怎么又过来了呀，哥哥哭惹” 🐱 ： “只可惜没见到你哈哈哈” 呜呜呜，小东西给我买了双椰子，还静悄悄的放到了办公室里，只留下一张小纸条 “匆忙来给你送它，886！”。\n其实我都知道，爱一个人想给一个人惊喜的过程既兴奋又紧张，独自做这件事的过程中也渴望温暖的反馈，她悄悄地来又悄悄地走。我多想瞬间出现轻轻地抱住这抹娇小的身躯。\n“宝贝，我爱你。”\n    2021年11月1日  十一月的第一天和她的同学们一起去了海洋公园，几人的热闹让我分外感觉到我和她关系的紧密，原来早已习惯了二人世界。\n浴缸、烛光，我轻轻地给她揉捏双腿。喝一口苏打水，这场景让我想到遥远的过去，亚当和夏娃依偎在山洞里躲雨的月夜。\n两只人体工学椅都到了，保护我们的腰迫在眉睫。\n     🥑 2021 October    2021年10月29日  褪去了夏日的炎热，金秋时节正是螃蟹肥嫩之时。去给小东西整了点螃蟹，似乎是蝤蠓的变种，倒是香甜。\n撒上葱姜盖上锅盖，让她看着小锅蒸螃蟹，我去冲凉，家的感觉越来越清晰了。\n她穿着素色长裙温柔极了👗。\n    2021年10月27日  她来Office找我，小富婆展示了一下余额3.8hkd的账户。\n中午思来想去不知道吃什么，去了上次和林毅吃饭的那栋楼，逛来逛去找到一家牛大人，味道还不错♨️。 Pu的事情一直缠绵在我们两个身上hhh。\n🐱 ： “我又拉屎了” 🐶 ： “哈哈哈 我刚才也去了”\n    2021年10月25日  一起上课的同学说：“你女朋友好可爱。” 我开心得不行。\n    2021年10月24日  蜘蛛侠夫妇去了鹤咀，我跟着他们港大的旅行团，倒是我们两个第一次出来郊游了。山间小路上我们聊了很多，云台记录了一些脚步，有她趴在鹅卵石上调整手机的样子，也有我在菠萝树下的忍耐不住。\n在蟹洞拍了很有感觉的合影，我和她要多留合影，把足迹留在各地，留待小崽子日后打卡追忆🗻。\n    2021年10月22日  High table dinner，她打扮的优雅大方。\n早饭吃了稻香，下午打了篮球，然后吃了楼下的蒸鱼。日子大多平平淡淡，因为是对的人所以有滋有味👩‍❤️‍👨。\n    2021年10月19日  因为一件不值得的事，没有关系的人，惹她不开心。很懊恼。\n分寸感很重要。希望以后也不留隔夜事。\n《恋爱守则》第一条：有问题解决问题，不要冷战。\n《恋爱守则》第二条：注意分寸感。\n    2021年10月15日  🐱 ： “尹先生，诚挚邀请您参与一场浪漫之旅，您准备好了吗？” 🐶 ： “我准备好了，但微信它没准备好（委屈）” 这一天，这一天啊，是她想给我惊喜来安慰我科研的压力，殊不知自己还顶着老板五天看300页毕业论文的任务。又是太子的旺角维景，梦开始的地方，泰坦尼克号的《我心永恒》十分应景🚢。1594。\n    2021年10月14日  🐱 ： “哥哥，为你开了个网店” 🐶 ： “啥子，what happened” 恭喜尹照元专属小店开业大吉，零加一产品只需52元。可惜我的支付宝一直有问题无法付款，被夏老师捷足先登了。\n门庭若市 ❌ 门可罗雀 ✅\n    2021年10月12日  娇俏的身姿坐在庄月明楼的大厅，弹着夜的钢琴曲五，是最斩我的样子🎹。\n瑞秋也在我们之间润色，她和姐姐的关系真好。\n⚽： “有了对象对我不好了，没有耐心也不温柔了，竟然说我夕阳黄昏，好恶毒”\n🐱 ： “所有温柔都给他了” 宝贝小嘴像抹了蜜似的🍯。\n    2021年10月9日  香港罕见的暴雨天，小东西胆子小的可怜，像只小仓鼠。\n🐱 ： “我感觉我被那个大叔盯上了，我下去了呜呜呜，心虚” 🐶 ： “笑死我了，我看谁敢拦宝贝！” 马辣的汤底还是那么不错，旺角到佐敦也没那么远，疫情的电影有些感人，小宝贝翔到临头有些有趣。大王叫我来巡山~~\n1599-1597\n    2021年10月7日  宝贝洗澡洗了个湿发淋漓。\n🐱 ： “我这个和老年人一样” 🐶 ： “没错，是哥哥想保护到老年的那个人” 看不得她皱眉，听不得她委屈嘟囔，即便在视频里。\n    2021年10月4日  今天去海洋公园玩耍，想不到小东西胆子还挺大，跟我把过山车坐了个遍，还有让她娇喘连连的海盗船。\n晚上尝试了花胶鸡煲，67kg来的猝不及防。看着她蹙起的眉间，我很难形容是种什么感觉，只是连白首的样子都想到了，我想这辈子就是这个宝贝了👫。\n    2021年10月2日  她妈妈也知道我们的相遇了。\n🐱 ： “我妈咪今天想看你，我把你耳钉给P了，发给她” 🐶 ： “！！怎么会这么丑，突然惊出一身汗” 🐱 ： “麻麻说看到我开心就也放心很多呀，在香港有人照顾我” 🐶 ： “那必须的呀” 爸爸妈妈们的了然虽然有点突然，但我又觉得一切都是水到渠成。我爸爸还查了“祎”的寓意是美好美玉💎，她说当年她大伯也是这么想的。\n    2021年10月1日  🐱 ： “要见到哥哥开心呀，小时候郊游的心情。” 国庆节也是办公室相聚的两个人。去吃了马辣台式火锅，拍了照片发给爸爸妈妈。 走遍西九龙的星光大道都没有发现一面国旗，她举着手机，手机里放着五星红旗🚩，我面朝大海唱着国歌。思绪回到年少时父亲教我国歌的夜晚，当时我们在天桥上等着妈妈下班回家。就那一瞬间我真的有想到这样的场景大抵也会在我的身上轮回吧，带着小崽子，等着她🌆。\n     🍒 2021 September    2021年9月30日  今天跟爸爸妈妈说了下和她的感情。P哥说得对，没什么要隐瞒的。这样的缘分应该得到他们的祝福。\n给小家伙挑了件可可爱爱的睡衣🐹。\n    2021年9月28日  🐱 ： “哥哥我和你说，我只要想到明天能见到你，就好开心哦。仿佛是终于等到家人来接我放学的感觉。” 🐶 ： “哥哥是个闷油瓶，好多话都憋在心里没说出来，爱你宝贝💖” 只好在这里记下一点点啦😃。\n    2021年9月26日  她在腰上差不多的地方，发现了和我一样的红点点。\n她的右手里有一只铅笔铅。 男左女右是么？当我们十指相扣的时候，面对面拥抱的时候便会悄然将这些记号严丝合缝。 晚上我走在回宿舍的路上，她委委屈屈的跟我说公式看不懂。傻孩子这些东西抽丝剥茧慢慢来，闻道有先后。小宝贝在电话里嘤嘤的啜泣，我的心跟着缩来缩去。\n在天愿作比翼鸟，在地愿为连理枝。\n    2021年9月25日  下午她来找我自习，晚上去吃了十八楼鸡煲，事实证明催姨妈效果很好。\n🐶 ： “我发现宝贝今晚很狂野啊” 🐱 ： “姨妈前的女人，你知道最厉害的是啥吗？无法无天，天不怕地不怕。” 嗯，为了伟大目标开始很认真的增重了，目标是67kg。\n    2021年9月21日  中秋在荃湾找了家五星级。晚上吃饭的人特别多，广场上络绎不绝的赏月的人们让我以为来到了盛唐。她头上戴着会发光的小兔耳朵站在小桥上，是除却月色与水色外人间的绝色。\n我刚把手指向挂在墙上的气球，她就像只小兔子似的跳起10厘米，而我嘴里的“宝贝，看看你能不能摸到”都还没有说出口。这样的心心相印不知道从什么时候开始。\n春寒赐浴华清池，温泉水滑洗凝脂。\n    2021年9月18日  搬到学校宿舍后相扑的机会就少了很多。\n🐱 ： “明天可不可以中午左右就见你” 🐶 ： “本来寻思晚上给宝贝个惊喜，但看着宝贝这么想哥哥，提前告诉你，晚上去接宝贝下课😎” 抱着她睡了一大觉。小东西早饭吃了虾饺、酸奶、麦片、蓝莓、橙子、三送饭、凤爪排骨饭。边吃边看《春娇与志明》。然后去KTV一展歌喉。\n她回去称了下体重，明明才53kg，却叫了我好几声臭猪，说我少的肉都跑她身上去了。\n    2021年9月17日  🐱 ： “梦里我记得咱们就像小朋友谈恋爱，不知咋滴你们一家来和我们一家玩，但是我们又没有称自己是在男女关系。但是大人们都心照不宣。” 🐶 ： “爸爸妈妈发现这孩子怎么跟我家宝贝那么搭，他俩不会就是天造地设的一对吧。” 三生三世的记忆慢慢在梦中浮现。\n    2021年9月15日  她穿着三眼仔配色的T恤背带裤来找我吃九龙塘的牛肉饭，还带了bakehouse的蛋挞。\n异地的每一天都充满思念，虽然经常被师兄说是在凡尔赛😕。\n    2021年9月12日  她今天和宿舍的同学去游泳了。\n哼，穿着白色战袍👙。\n    2021年9月9日  🐱 ： “有空的时候帮我康康电扇哦，不太习惯没有小风吹吹的感觉。” 小叠词都用起来了，每天都在脑海里想想她可爱的样子。还说我上辈子是碳酸饮料，因为看到我就开心得冒泡。\n哼哼，那我看你是薄荷糖，让我冒泡个不停🍹。\n    2021年9月7日  上一次睡子母床给她脖子整落枕了，这两天一直哼哼，可怜兮兮。\n她的小风扇还坏了，真是可怜的小家伙。\n我跟🐷哥拍完教师节的视频之后，想着给她个惊喜，悄悄的坐上了去港岛的地铁。 🐶 ： “送送🐷哥” 🐱 ： “你送他？那你来接我吧哈哈哈” 🐶 ： “宝贝呀宝贝，我刚跟P哥说你想不到我要去找你，没想到宝贝完全不上套呀” 🐱 ： “咋两个，心有灵犀” 量子纠缠了属于是。\n    2021年9月4日  第一次超过36小时的相聚。\n她送了我一只博朗S9剃须刀 🐱 ： “就想给你一次终结嘛” 小傻瓜，有你作为终结就够了。\n    2021年9月3日  今天她要去深圳海关办理visa的延期，虽然中间出了点状况，但好在都顺利完成了。\n晚上去把她接回太子。我的拥抱应该可以缓解劳累吧。      🍑 2021 August    2021年8月31日  开了一晚上的组会，拼了会乐高缓和下情绪才回的家，结果给她打电话不通。\n🐱 ： “想抱抱你 字面意思” 🐶 ： “啊？” 🐱 ： “你开门” 我曾以为这种浪漫只存在于电视剧中，没想到也出现在我的面前。世间任何情话都不及你柔软的怀抱。\n     2021年8月30日\n 🐱 ： “晚霞送去我的思念 mua” 🐶 ： “晚霞再美不及你眼眸的颜色” 🐱 ： “因为我的眼眸里都是你呀 biubiubiu” 见不到的每一天都是度日如年。你 si 嗯 gi biebai 👶。\n     2021年8月27日\n 第一次一起游泳，前奏是电梯的调度问题。\n然后去莲香楼吃了很不错的蒸鱼，再回太子。\n嘻嘻，小圆也很热情😴。\n     2021年8月25日\n 今天她离开黄埔老家了，我们也不再去那条海岸线。\n坚尼地城的风光也还好，就是那个乾隆鸡煲做的像💩一样。\n八月光风霁月天，未曾与晚风说再见。\n     2021年8月23日\n 她房间空调坏了。\n嗯，她说我是坏哥哥，小左小右都记一下😈。\n     2021年8月22日\n 去看了R级片《自杀特攻》，无聊的很。 又去巴依吃了大盘鸡，撑得很。\n     2021年8月21日\n 中午送她回去的时候编了《三只小猪》的故事，下午又给她姐姐写了份检讨，以致宫寒之歉。 🐱 ：“我感觉真的冥冥之中，你大概就是那个人吧哈哈哈哈哈哈” 🐶 ： “还大概呢，哼。”      2021年8月20日\n 今天去CUHK找了🐷哥，晚点的时候跟他们一起玩了会德州扑克。\n🐱 ：“今儿有点烦躁，晚上要不你别来了吧” 我把手上的筹码一把梭哈就跑了起来，三公里的路十来分钟就跑完了。半个小时后我出现在她面前，眼睛还红红的。\n“在我肩上哭吧，来姨妈就该随心所欲。” 之后她第一次跟我回太子。🐷哥跟我说，这样以后会很累。我跟他说，爱一次就要这么用力。\n     2021年8月19日\n 忙了一周的Qualify exam终于交上去了。小东西花300元买牙膏就为了送的几瓶洗衣液。。。\n晚上她第一次来我的太子老家做客（送洗衣液和牙膏），我给她调了mojito。葡萄美酒夜光杯🍷。\n     2021年8月18日\n 下午她摸鱼去了沙田的那个博物馆，我让她模仿我的动作拍一张李小龙蹬腿。\n好家伙，国民党伪军看着都比她正规。照🐅画🐈。\n     2021年8月15日\n “报告，没有作弊，纯属默契。”\n蓝色T恤，绿色裤子。身无彩凤双飞翼，心有灵犀一点通。想上九天问问月老，什么时候把红线的材质换成碳60了。\n     2021年8月14日\n 七夕，中午去吃了牛涮锅，然后送了她一只小西几，希望能替我陪伴未能出现在她身边的那些时刻。\n晚上去黄埔的小区打了篮球，她令我大吃一惊，运动天赋确实惊人。\n     2021年8月13日\n 🐶 ： “哥哥来了，出发！” 🐱 ： “您的宝贝暂时下线。您好，现诚挚地邀请您参与寻宝活动，请问您准备好了吗？” 🐶 ： “嘶” 🐱 ： “一闪一闪亮晶晶，按照提示线索到指定地点。（考验默契的时候到了” 🐶 ： “不会是那个座位吧” 🐱 ： “一点儿不好玩，臭猪，你快来！” 情人节的前夜，她跟我玩寻宝游戏，总是那么的古灵精怪。但我瞻前顾后，担心去错了地方，最后还是等了一个明确的答案才出发，确实是一头蠢猪了。\n她送了我一辆保时捷911的乐高模型，我送了她一个坐垫。蠢上加蠢了属于是 🐷🐷。\n     2021年8月12日\n 🐱 ： “你知道你像什么嘛？” 🐶 ： “像啥” 🐱 ： “像地球一样吸引着我” 🐶 ： “哈哈哈哈还是你行啊我都江郎才尽了” 之前从未觉得这些情话也会属于我。\n8月的晚上尽在黄埔度过，今天在她脖子侧面留了个小草莓，粉粉的，很可爱 🍓。\n     2021年8月10日\n 🐱 ： “n 55！W !” 🐶 ： “太抽象了” “I miss u” 春娇与志明里的桥段，她这样跟我说的。晚上发掘了“一闪一闪亮晶晶”，还一起喝了1664。\n     2021年8月9日\n 🐱 ： “你下次把我要是惹哭了，那可哄不好，没那么容易” 🐶 ： “小生最擅哄孩子了，把我弟弟哄得明明白白的，想必宝贝也是手到擒来” 那时我还年轻，不知道她是水做的，豆大的泪珠说掉就掉 💦。\n     2021年8月7日\n 🐱 ： “咱俩选个日子谈恋爱吧哈哈哈哈哈哈就8.8吧哈哈哈哈哈哈哈哈哈” 🐶 ： “哈哈哈哈这还要定日子呢？” 🐱 ： “给你个名分，你要不要嘛” 🐶 ： “要呗 😎” 她要给我个名分，我说今晚就在一起吧 💓\n生命中我遇到了许多人，睁开眼第一个看到的叫做父母，一起长大的叫做发小，课堂上互相讨论的叫做同学，玩得开心合得来的叫做朋友，教导我知识技能的叫做老师，看不顺眼的叫做可恶的家伙\u0026hellip;，和这些人的喜怒哀乐构成了我23年来一天天的日子。今天我终于有一个合情合理叫做宝贝的人儿了，未来的每一天里都将充斥着她的音容笑貌，我不知道那是种什么感觉，但已经开始希冀起来。 今天是我的生日，我没有告诉她，直到23:59:59。🐷哥送的Popmart还分了一个给她 🎂。\n     2021年8月6日\n 🐶 ： “宝贝，蜗牛都爬下来了 👊” 🐱 ： “？？？你认真的啊，我以为你乱说” 去海滨长廊探险，我没戴眼镜，她说要做我的导航，领的路甚少有碳基生物🙏。\n     2021年8月5日\n 🐱 ： “你还在office吗？” 🐶 ： “在呀” 🐱 ： “举报你摸鱼！和我聊天！😎 ” 🐶 ： “。” 晚上一起去吃了湖南菜馆，她说第一次看我脸红？？？\n蓝色背带裤yyds。\n     2021年8月4日\n 🐱 ： “问个问题，如果说在一起之后又遇到了让你心动或者是觉得更好的怎么办？毕竟得不到的永远在骚动是吧” 🐶 ： “爷们最恨见异思迁，做不到的事情不要轻易许诺。” 那天晚上我们聊了很多，我埋怨她不给我发消息，她说害怕自己期待别人的消息。我很难形容那一刻自己的心情，她喜欢我么？为什么我没有欣喜若狂？为什么心里是一种跨过岁月重逢时的释怀？\n我不明白，但我发现比起网上丰富多彩的舔狗和高富帅，这好像才是爱情该有的样子。\n     2021年8月3日\n 🐱 ： “我凭我女人的第六感，我觉得你虽然线上对女孩子油嘴滑舌的很不靠谱的样子，感觉真正谈恋爱的时候你应该是靠谱的” 🐶 ： “哈哈哈哈哈哈臭宝待会下楼” 小东西，被你看穿了 😌。\n     2021年8月2日\n 🐶 ： “宝贝，我还有机会么” 🐱 ： “海滨南岸八点半” 不约而同的C2出口，我看到一个盛夏天穿着羊毛衫的小可爱。飘散经久的灵魂选择了默契，我和她的故事开始了。\n     🍉 2021 July     2021年7月23日\n 🐶 ： “靠！我这周把这里忘了，好兄弟你别生气 😛” 🐱 ： “一顿饭都不够弥补的，大概要三顿吧 😋”·\n·\n·\n 🐱 ： “人生建议，喜欢我，哈哈哈哈没有表情包一点不可爱” 🐶 ： “懂了，宁就是海王！” 这波是把学习的枯燥都发泄出来了 😈。\n     2021年7月14日\n 🐱 ： “哈哈哈哈我们仿佛有时差” 🐶 ： “彼此生活在日子的缝隙里吧” 🐱 ： “等明天的生活缝隙里我会想起你的” 啧啧啧，她顺坡下驴的功夫真好。\n     2021年7月13日\n 🐶 ： “hi” 🐱 ： “hi” 香港的夏天那么炎热，我们在青藤旁认识。\n   ","date":33183043200,"expirydate":-62135596800,"kind":"page","lang":"en","lastmod":33183043200,"objectID":"29c714119bfe6565b3fc55af440a24af","permalink":"https://enjoy1415.github.io/post/moments/","publishdate":"0001-01-01T00:00:00Z","relpermalink":"/post/moments/","section":"post","summary":"Hold your hands through mountains and sea, until the last living day. :heart:","tags":[],"title":"Days with biebai.","type":"post"},{"authors":[],"categories":null,"content":" Click on the Slides button above to view the built-in slides feature.   Slides can be added in a few ways:\n Create slides using Wowchemy\u0026rsquo;s Slides feature and link using slides parameter in the front matter of the talk file Upload an existing slide deck to static/ and link using url_slides parameter in the front matter of the talk file Embed your slides (e.g. Google Slides) or presentation video on this page using shortcodes.  Further event details, including page elements such as image galleries, can be added to the body of this page.\n","date":1906549200,"expirydate":-62135596800,"kind":"page","lang":"en","lastmod":1906549200,"objectID":"96344c08df50a1b693cc40432115cbe3","permalink":"https://enjoy1415.github.io/talk/example/","publishdate":"2017-01-01T00:00:00Z","relpermalink":"/talk/example/","section":"talk","summary":"An example talk using Wowchemy's Markdown slides feature.","tags":[],"title":"Example Talk","type":"talk"},{"authors":["Yin Zhaoyuan"],"categories":[],"content":"\n ✨   Github上的代码会被运到北极冻土层里保存上千年，人类智慧的结晶便流浪地球，留与后世之人。\n千年太短，我要浩瀚的宇宙见证我们的相遇。射手座星云RA 18h00m29.06 -23°21'15.2'' dec 10.17 mag Sgr的星星我看着很亮，黄灿灿的星光也美得像我们的爱情。 我叫它“金想想 NO.1”，一如我常在你耳边的低语。今年是No.1，明年是NO.2，等把天上的星星全都用完了，我再想其他接近无穷的办法来逼近我们的永恒。我还挑了一只Swarovski Constella系列的手链，听说寓意也是天上的星光，希望它们交相呼应，陪伴我们走完一段段路程。\n  金想想 NO.1\n https://osr.org/oms/en/XDZ362448\n   宝贝，生日快乐。难免有些理想主义之寡淡，其实是哥哥的一点浪漫。\n 惟江上之清风，与山间之明月，耳得之而为声，目遇之而成色。 \u0026mdash;《苏轼·前赤壁赋》\n ","date":1638537306,"expirydate":-62135596800,"kind":"page","lang":"en","lastmod":1638537306,"objectID":"ae7845953d763a4880ff70562031a38f","permalink":"https://enjoy1415.github.io/post/birthday/","publishdate":"0001-01-01T00:00:00Z","relpermalink":"/post/birthday/","section":"post","summary":"I named a star as '金想想 NO.1' in Sagittarius for your 23trd birthday gift. :birthday:","tags":[],"title":"Happy birthday my sweetheart!","type":"post"},{"authors":["Yin Zhaoyuan","Fang Chao","Yang Haoxiang","Fang Yiping","Xie Min"],"categories":null,"content":"","date":1636502400,"expirydate":-62135596800,"kind":"page","lang":"en","lastmod":1636502400,"objectID":"15a5d9b1e10f60dfb3524178cd034935","permalink":"https://enjoy1415.github.io/publication/dro/","publishdate":"2021-11-10T00:00:00Z","relpermalink":"/publication/dro/","section":"publication","summary":"A journal paper targeted to Risk Analysis","tags":[],"title":"Improving the resilience of power grids against typhoons with data-driven spatial distributionally robust optimization","type":"publication"},{"authors":["Yin Zhaoyuan"],"categories":null,"content":"\n 👩‍❤️‍👨    如果不曾遇到你，我或许不会相信爱情吧，金祎。\n 我向来不是一个对感情充满乐观的人。因为情感这种东西从来不能放到称上量一量几斤几两，所以两个人的关系里也便没有客观意义上的公平。不愿成为那个失败者又见过太多离别，最后连自己也慢慢失了开口寻找的勇气。\n可月老的红线就像吹灭蜡烛后的那缕烟丝，你看它悬而又悬飘渺不定，但偏偏穷且益坚，只待点点火星便把烛火循迹燃起。且不说相识时我们是如何两天打鱼三天晒网，也不说那些“我叫你宝，你叫我贝”的骚话，就一句“宝，我还有机会么？”便仿佛一对把日子全过了一遍，又经历了不少白首难忘分散的恋人。那时我们还未曾谋面。\n “宝贝，我还有机会么？”\n  “你快别放屁了！”\n 最初的美好流淌在八月盛夏的晚上。初见、再见、牵手，这一切美妙的像一场梦。你说要给我个名分的时候，我脑子里忽然想起那句话“一鼓作气，再而衰，三而竭”，天天喊我臭猪撒娇的小家伙原来才是那位勇士，携我突入爱情的高地。多少个盛夏的夜晚，我脑海里弹出你娇俏的小脸，洋洋得意的如一个凯旋的将军。\n “咱俩选个日子谈恋爱吧哈哈哈就8.8吧哈哈哈哈哈哈哈哈哈”\n 宝贝，哥哥嘴笨，哥哥不知道怎么描述我们开始的每一分每一秒，哥哥爱你。\n","date":1628294400,"expirydate":-62135596800,"kind":"page","lang":"en","lastmod":1628294400,"objectID":"0d401a6bfd36ba759cebd824acfe69ed","permalink":"https://enjoy1415.github.io/post/begining/","publishdate":"2021-08-07T00:00:00Z","relpermalink":"/post/begining/","section":"post","summary":"I love all the stars in the sky，but they are nothing compared to the ones in your eyes. :waning_gibbous_moon:","tags":null,"title":"I'm in love with you, he said quietly.","type":"post"},{"authors":[],"categories":[],"content":"Create slides in Markdown with Wowchemy Wowchemy | Documentation\n Features  Efficiently write slides in Markdown 3-in-1: Create, Present, and Publish your slides Supports speaker notes Mobile friendly slides   Controls  Next: Right Arrow or Space Previous: Left Arrow Start: Home Finish: End Overview: Esc Speaker notes: S Fullscreen: F Zoom: Alt + Click PDF Export: E   Code Highlighting Inline code: variable\nCode block:\nporridge = \u0026quot;blueberry\u0026quot; if porridge == \u0026quot;blueberry\u0026quot;: print(\u0026quot;Eating...\u0026quot;)   Math In-line math: $x + y = z$\nBlock math:\n$$ f\\left( x \\right) = ;\\frac{{2\\left( {x + 4} \\right)\\left( {x - 4} \\right)}}{{\\left( {x + 4} \\right)\\left( {x + 1} \\right)}} $$\n Fragments Make content appear incrementally\n{{% fragment %}} One {{% /fragment %}} {{% fragment %}} **Two** {{% /fragment %}} {{% fragment %}} Three {{% /fragment %}}  Press Space to play!\nOne  Two  Three \n A fragment can accept two optional parameters:\n class: use a custom style (requires definition in custom CSS) weight: sets the order in which a fragment appears   Speaker Notes Add speaker notes to your presentation\n{{% speaker_note %}} - Only the speaker can read these notes - Press `S` key to view {{% /speaker_note %}}  Press the S key to view the speaker notes!\n Only the speaker can read these notes Press S key to view    Themes  black: Black background, white text, blue links (default) white: White background, black text, blue links league: Gray background, white text, blue links beige: Beige background, dark text, brown links sky: Blue background, thin dark text, blue links    night: Black background, thick white text, orange links serif: Cappuccino background, gray text, brown links simple: White background, black text, blue links solarized: Cream-colored background, dark green text, blue links   Custom Slide Customize the slide style and background\n{{\u0026lt; slide background-image=\u0026quot;/media/boards.jpg\u0026quot; \u0026gt;}} {{\u0026lt; slide background-color=\u0026quot;#0000FF\u0026quot; \u0026gt;}} {{\u0026lt; slide class=\u0026quot;my-style\u0026quot; \u0026gt;}}   Custom CSS Example Let\u0026rsquo;s make headers navy colored.\nCreate assets/css/reveal_custom.css with:\n.reveal section h1, .reveal section h2, .reveal section h3 { color: navy; }   Questions? Ask\nDocumentation\n","date":1549324800,"expirydate":-62135596800,"kind":"page","lang":"en","lastmod":1549324800,"objectID":"0e6de1a61aa83269ff13324f3167c1a9","permalink":"https://enjoy1415.github.io/slides/example/","publishdate":"2019-02-05T00:00:00Z","relpermalink":"/slides/example/","section":"slides","summary":"An introduction to using Wowchemy's Slides feature.","tags":[],"title":"Slides","type":"slides"},{"authors":null,"categories":null,"content":"Lorem ipsum dolor sit amet, consectetur adipiscing elit. Duis posuere tellus ac convallis placerat. Proin tincidunt magna sed ex sollicitudin condimentum. Sed ac faucibus dolor, scelerisque sollicitudin nisi. Cras purus urna, suscipit quis sapien eu, pulvinar tempor diam. Quisque risus orci, mollis id ante sit amet, gravida egestas nisl. Sed ac tempus magna. Proin in dui enim. Donec condimentum, sem id dapibus fringilla, tellus enim condimentum arcu, nec volutpat est felis vel metus. Vestibulum sit amet erat at nulla eleifend gravida.\nNullam vel molestie justo. Curabitur vitae efficitur leo. In hac habitasse platea dictumst. Sed pulvinar mauris dui, eget varius purus congue ac. Nulla euismod, lorem vel elementum dapibus, nunc justo porta mi, sed tempus est est vel tellus. Nam et enim eleifend, laoreet sem sit amet, elementum sem. Morbi ut leo congue, maximus velit ut, finibus arcu. In et libero cursus, rutrum risus non, molestie leo. Nullam congue quam et volutpat malesuada. Sed risus tortor, pulvinar et dictum nec, sodales non mi. Phasellus lacinia commodo laoreet. Nam mollis, erat in feugiat consectetur, purus eros egestas tellus, in auctor urna odio at nibh. Mauris imperdiet nisi ac magna convallis, at rhoncus ligula cursus.\nCras aliquam rhoncus ipsum, in hendrerit nunc mattis vitae. Duis vitae efficitur metus, ac tempus leo. Cras nec fringilla lacus. Quisque sit amet risus at ipsum pharetra commodo. Sed aliquam mauris at consequat eleifend. Praesent porta, augue sed viverra bibendum, neque ante euismod ante, in vehicula justo lorem ac eros. Suspendisse augue libero, venenatis eget tincidunt ut, malesuada at lorem. Donec vitae bibendum arcu. Aenean maximus nulla non pretium iaculis. Quisque imperdiet, nulla in pulvinar aliquet, velit quam ultrices quam, sit amet fringilla leo sem vel nunc. Mauris in lacinia lacus.\nSuspendisse a tincidunt lacus. Curabitur at urna sagittis, dictum ante sit amet, euismod magna. Sed rutrum massa id tortor commodo, vitae elementum turpis tempus. Lorem ipsum dolor sit amet, consectetur adipiscing elit. Aenean purus turpis, venenatis a ullamcorper nec, tincidunt et massa. Integer posuere quam rutrum arcu vehicula imperdiet. Mauris ullamcorper quam vitae purus congue, quis euismod magna eleifend. Vestibulum semper vel augue eget tincidunt. Fusce eget justo sodales, dapibus odio eu, ultrices lorem. Duis condimentum lorem id eros commodo, in facilisis mauris scelerisque. Morbi sed auctor leo. Nullam volutpat a lacus quis pharetra. Nulla congue rutrum magna a ornare.\nAliquam in turpis accumsan, malesuada nibh ut, hendrerit justo. Cum sociis natoque penatibus et magnis dis parturient montes, nascetur ridiculus mus. Quisque sed erat nec justo posuere suscipit. Donec ut efficitur arcu, in malesuada neque. Nunc dignissim nisl massa, id vulputate nunc pretium nec. Quisque eget urna in risus suscipit ultricies. Pellentesque odio odio, tincidunt in eleifend sed, posuere a diam. Nam gravida nisl convallis semper elementum. Morbi vitae felis faucibus, vulputate orci placerat, aliquet nisi. Aliquam erat volutpat. Maecenas sagittis pulvinar purus, sed porta quam laoreet at.\n","date":1461715200,"expirydate":-62135596800,"kind":"page","lang":"en","lastmod":1461715200,"objectID":"e8f8d235e8e7f2efd912bfe865363fc3","permalink":"https://enjoy1415.github.io/project/example/","publishdate":"2016-04-27T00:00:00Z","relpermalink":"/project/example/","section":"project","summary":"An example of using the in-built project page.","tags":["Deep Learning"],"title":"Example Project","type":"project"}]